karkipytranslator/__init__.py
karkipytranslator/main.py
karkipytranslator/yandex.py
karkipytranslator-0.1.0.dist-info/LICENSE
karkipytranslator-0.1.0.dist-info/METADATA
karkipytranslator-0.1.0.dist-info/WHEEL
karkipytranslator-0.1.0.dist-info/top_level.txt
karkipytranslator-0.1.0.dist-info/RECORD
