Metadata-Version: 2.1
Name: karkipytranslator
Version: 0.1.0
Summary: A language translator package
Home-page: https://github.com/karkipy/pytranslator
Author: Aashish Karki
Author-email: aashish.y2z@gmail.com
License: UNKNOWN
Platform: UNKNOWN
Classifier: Programming Language :: Python :: 3
Classifier: License :: OSI Approved :: MIT License
Classifier: Operating System :: OS Independent
